PolibaseAppService/__init__.py
PolibaseAppService/__main__.py
PolibaseAppService/const.py
PolibaseAppService/service.py
pih_plb_app-1.22.dist-info/METADATA
pih_plb_app-1.22.dist-info/WHEEL
pih_plb_app-1.22.dist-info/entry_points.txt
pih_plb_app-1.22.dist-info/top_level.txt
pih_plb_app-1.22.dist-info/RECORD
