Metadata-Version: 2.1
Name: pih-plb-app
Version: 1.22
Summary: PIH Polibase Application service package
Home-page: https://pacifichosp.com/
Author: Nikita Karachentsev
Author-email: it@pacifichosp.com
License: MIT
Requires-Dist: ipih
